reley/__init__.py
reley/__release_info__.py
reley/prelude.hs
reley/impl/__init__.py
reley/impl/cli.py
reley/impl/compiler.py
reley/impl/expr_based_ast.py
reley/impl/grammar.py
reley/impl/grammar.rbnf
reley/impl/helper.py
reley/impl/precedence.py
reley/impl/pycompat.py
reley/impl/reley_import.py
reley-0.1.18.dist-info/METADATA
reley-0.1.18.dist-info/RECORD
reley-0.1.18.dist-info/WHEEL
reley-0.1.18.dist-info/entry_points.txt
reley-0.1.18.dist-info/top_level.txt
